langcycle/__init__.py
langcycle-0.0.2.dist-info/LICENSE
langcycle-0.0.2.dist-info/METADATA
langcycle-0.0.2.dist-info/WHEEL
langcycle-0.0.2.dist-info/entry_points.txt
langcycle-0.0.2.dist-info/top_level.txt
langcycle-0.0.2.dist-info/RECORD
