Metadata-Version: 2.1
Name: langcycle
Version: 0.0.2
Summary: Cycles keyboard input layouts using setxkbmap
Home-page: UNKNOWN
Author: Benoit Clennett-Sirois
Author-email: benoitcsirois@gmail.com
License: MIT
Keywords: setxkbmap,keyboard,layout
Platform: UNKNOWN
License-File: LICENSE
Provides-Extra: test
Requires-Dist: pytest ; extra == 'test'
Requires-Dist: pytest-mypy ; extra == 'test'
